nvidia_tao_cli/__init__.py
nvidia_tao_cli/version.py
nvidia_tao_cli/components/__init__.py
nvidia_tao_cli/components/docker_handler/__init__.py
nvidia_tao_cli/components/docker_handler/docker_handler.py
nvidia_tao_cli/components/instance_handler/__init__.py
nvidia_tao_cli/components/instance_handler/base_instance.py
nvidia_tao_cli/components/instance_handler/builder.py
nvidia_tao_cli/components/instance_handler/local_instance.py
nvidia_tao_cli/components/instance_handler/utils.py
nvidia_tao_cli/components/instance_handler/whl_instance.py
nvidia_tao_cli/components/types/__init__.py
nvidia_tao_cli/components/types/task.py
nvidia_tao_cli/config/__init__.py
nvidia_tao_cli/config/config.json
nvidia_tao_cli/config/config_deploy.json
nvidia_tao_cli/entrypoint/__init__.py
nvidia_tao_cli/entrypoint/tao_launcher.py
nvidia_tao-6.25.11.dist-info/LICENSE
nvidia_tao-6.25.11.dist-info/METADATA
nvidia_tao-6.25.11.dist-info/WHEEL
nvidia_tao-6.25.11.dist-info/entry_points.txt
nvidia_tao-6.25.11.dist-info/top_level.txt
nvidia_tao-6.25.11.dist-info/RECORD
