Metadata-Version: 2.1
Name: nvidia-tao
Version: 6.25.11
Summary: NVIDIA's Launcher for TAO Toolkit.
Home-page: UNKNOWN
Author: Varun Praveen
Author-email: vpraveen@nvidia.com
License: NVIDIA Proprietary Software
Keywords: nvidia,tao,launcher
Platform: UNKNOWN
Classifier: Intended Audience :: Developers
Classifier: Topic :: Software Development :: Libraries
Classifier: Topic :: Software Development :: Libraries :: Python Modules
Classifier: Environment :: Console
Classifier: Operating System :: POSIX :: Linux
Classifier: License :: OSI Approved :: Apache Software License
Classifier: Programming Language :: Python :: 3
Classifier: Topic :: Scientific/Engineering :: Artificial Intelligence
Requires-Python: >=3.6
License-File: LICENSE
Requires-Dist: certifi (>=2022.12.07)
Requires-Dist: chardet (==3.0.4)
Requires-Dist: docker-pycreds (==0.4.0)
Requires-Dist: docker (==4.3.1)
Requires-Dist: idna (==2.10)
Requires-Dist: requests (==2.31.0)
Requires-Dist: rich (<14.0,>=13.6.0)
Requires-Dist: six (<2.0.0,>=1.15.0)
Requires-Dist: tabulate (<1.0,>=0.9.0)
Requires-Dist: urllib3 (<2.0.0,>=1.26.15)
Requires-Dist: websocket-client (==0.57.0)
